README.txt
setup.py
Django_TimelineJS.egg-info/PKG-INFO
Django_TimelineJS.egg-info/SOURCES.txt
Django_TimelineJS.egg-info/dependency_links.txt
Django_TimelineJS.egg-info/top_level.txt
timelinejs/
timelinejs/__init__.py
timelinejs/admin.py
timelinejs/models.py
timelinejs/static
timelinejs/templates
timelinejs/templatetags
timelinejs/urls.py
timelinejs/views.py
timelinejs/static/admin
timelinejs/static/css
timelinejs/static/js
timelinejs/static/admin/css
timelinejs/static/admin/js
timelinejs/static/admin/css/editor.css
timelinejs/static/admin/js/editor.js
timelinejs/static/admin/js/inlinecollapsed.js
timelinejs/static/css/loading.gif
timelinejs/static/css/themes
timelinejs/static/css/timeline.css
timelinejs/static/css/timeline.png
timelinejs/static/css/themes/dark.css
timelinejs/static/css/themes/font
timelinejs/static/css/themes/timeline-dark.png
timelinejs/static/css/themes/timeline-texture.png
timelinejs/static/css/themes/font/AbrilFatface-Average.css
timelinejs/static/css/themes/font/Arvo-PTSans.css
timelinejs/static/css/themes/font/Bevan-PotanoSans.css
timelinejs/static/css/themes/font/BreeSerif-OpenSans.css
timelinejs/static/css/themes/font/DroidSerif-DroidSans.css
timelinejs/static/css/themes/font/Georgia-Helvetica.css
timelinejs/static/css/themes/font/Lekton-Molengo.css
timelinejs/static/css/themes/font/Lora-Istok.css
timelinejs/static/css/themes/font/Merriweather-NewsCycle.css
timelinejs/static/css/themes/font/NewsCycle-Merriweather.css
timelinejs/static/css/themes/font/NixieOne-Ledger.css
timelinejs/static/css/themes/font/PT.css
timelinejs/static/css/themes/font/PTSerif-PTSans.css
timelinejs/static/css/themes/font/Pacifico-Arimo.css
timelinejs/static/css/themes/font/PlayfairDisplay-Muli.css
timelinejs/static/css/themes/font/PoiretOne-Molengo.css
timelinejs/static/css/themes/font/Rancho-Gudea.css
timelinejs/static/css/themes/font/SansitaOne-Kameron.css
timelinejs/static/js/locale
timelinejs/static/js/storyjs-embed.js
timelinejs/static/js/timeline-min.js
timelinejs/static/js/timeline.js
timelinejs/static/js/locale/ar.js
timelinejs/static/js/locale/bg.js
timelinejs/static/js/locale/ca.js
timelinejs/static/js/locale/cz.js
