Metadata-Version: 1.1
Name: Django-TimelineJS
Version: 0.2
Summary: Pluggable app for Django to edit and display TimelineJS timelines
Home-page: https://github.com/abdallah/Django-TimelineJS
Author: Abdallah Deeb
Author-email: abdallah@deeb.me
License: MPL2.0
Download-URL: https://github.com/abdallah/Django-TimelineJS/zipball/master
Platform: UNKNOWN
Classifier: Development Status :: 4 - Beta
Classifier: Framework :: Django
Classifier: Environment :: Web Environment
Classifier: Intended Audience :: Developers
Classifier: License :: OSI Approved :: Mozilla Public License 2.0 (MPL 2.0)
Classifier: Programming Language :: Python
Classifier: Topic :: Internet :: WWW/HTTP
